libnagios/__init__.py
libnagios/doc.py
libnagios/exceptions.py
libnagios/plugin.py
libnagios/types.py
libnagios/utils.py
libnagios/checks/__init__.py
libnagios/checks/check_cp_bitlocker.py
libnagios/checks/check_cp_cpu.py
libnagios/checks/check_cp_disk.py
libnagios/checks/check_cp_load.py
libnagios/checks/check_cp_procs.py
libnagios/checks/check_cp_ssh.py
libnagios/checks/check_cp_swap.py
cp_nagios_plugins-0.7.6.dist-info/METADATA
cp_nagios_plugins-0.7.6.dist-info/WHEEL
cp_nagios_plugins-0.7.6.dist-info/entry_points.txt
cp_nagios_plugins-0.7.6.dist-info/licenses/LICENSE
cp_nagios_plugins-0.7.6.dist-info/RECORD
